nice_oom/__init__.py
nice_oom/__main__.py
nice_oom_daemon-0.0.1.data/data/LICENSE
nice_oom_daemon-0.0.1.data/data/README.md
nice_oom_daemon-0.0.1.data/data/VERSION
nice_oom_daemon-0.0.1.dist-info/DESCRIPTION.rst
nice_oom_daemon-0.0.1.dist-info/METADATA
nice_oom_daemon-0.0.1.dist-info/RECORD
nice_oom_daemon-0.0.1.dist-info/WHEEL
nice_oom_daemon-0.0.1.dist-info/entry_points.txt
nice_oom_daemon-0.0.1.dist-info/metadata.json
nice_oom_daemon-0.0.1.dist-info/top_level.txt
